{
  "generated_at": "2025-12-17T12:58:38.217550+08:00",
  "total_titles_processed": 306,
  "failed_sources": [],
  "trends": [
    {
      "keyword_group": "美国",
      "match_count": 8,
      "titles": [
        {
          "title": "美国就业继续降温：11月非农小幅回升，但失业率创四年新高，交易员估明年降息两次",
          "url": "https://wallstreetcn.com/articles/3761504",
          "source": "华尔街见闻",
          "ranks": [
            2
          ],
          "is_new": false,
          "appearance_count": 1,
          "time_info": "12时58分"
        },
        {
          "title": "美国11月非农录得6.4万人 失业率为四年来新高 劳动力市场面临不确定性",
          "url": "https://www.cls.cn/detail/2231468",
          "source": "财联社热门",
          "ranks": [
            3
          ],
          "is_new": false,
          "appearance_count": 1,
          "time_info": "12时58分"
        },
        {
          "title": "美国同意提供安全保障，欧洲多方欢迎“重大进展”，美乌“和平计划”将提交俄方",
          "url": "https://wallstreetcn.com/articles/3761522",
          "source": "华尔街见闻",
          "ranks": [
            9
          ],
          "is_new": false,
          "appearance_count": 1,
          "time_info": "12时58分"
        },
        {
          "title": "经济数据难解美国经济迷雾 三大期指横盘震荡 | 今夜看点",
          "url": "https://www.cls.cn/detail/2231451",
          "source": "财联社热门",
          "ranks": [
            9
          ],
          "is_new": false,
          "appearance_count": 1,
          "time_info": "12时58分"
        },
        {
          "title": "美国务院批准1亿美元对日军售",
          "url": "https://www.douyin.com/hot/2338714",
          "source": "抖音",
          "ranks": [
            14
          ],
          "is_new": false,
          "appearance_count": 1,
          "time_info": "12时58分"
        },
        {
          "title": "美国版战忽局再上线",
          "url": "https://search.bilibili.com/all?keyword=%E7%BE%8E%E5%9B%BD%E7%89%88%E6%88%98%E5%BF%BD%E5%B1%80%E5%86%8D%E4%B8%8A%E7%BA%BF",
          "source": "bilibili 热搜",
          "ranks": [
            24
          ],
          "is_new": false,
          "appearance_count": 1,
          "time_info": "12时58分"
        },
        {
          "title": "许亚军被曝在美国",
          "url": "https://www.toutiao.com/trending/7583827299838066724/",
          "source": "今日头条",
          "ranks": [
            26
          ],
          "is_new": false,
          "appearance_count": 1,
          "time_info": "12时58分"
        },
        {
          "title": "国台办：坚决反对美国与中国台湾地区开展任何形式的军事联系",
          "url": "https://wallstreetcn.com/livenews/3022095",
          "source": "华尔街见闻-快讯",
          "ranks": [
            29
          ],
          "is_new": false,
          "appearance_count": 1,
          "time_info": "12时58分"
        }
      ]
    },
    {
      "keyword_group": "AI 人工智能",
      "match_count": 7,
      "titles": [
        {
          "title": "凯投宏观：如果AI热潮继续消退，中国股市可能比美国股市表现更好",
          "url": "https://flash.jin10.com/detail/20251217124326326800",
          "source": "金十数据",
          "ranks": [
            2
          ],
          "is_new": false,
          "appearance_count": 1,
          "time_info": "12时58分"
        },
        {
          "title": "成都 35 所中小学试点 AI 批改作业，准确率达 95%，如何评价这种批改形式？会全国推广吗？",
          "url": "https://www.zhihu.com/question/1984358783053422759",
          "source": "知乎",
          "ranks": [
            5
          ],
          "is_new": false,
          "appearance_count": 1,
          "time_info": "12时58分"
        },
        {
          "title": "新加坡金管局调查：经济学家指出地缘政治和人工智能泡沫是新加坡经济的潜在风险。科技周期、全球增长和贸易紧张局势缓和可能是潜在的顺风。",
          "url": "https://flash.jin10.com/detail/20251217120220101800",
          "source": "金十数据",
          "ranks": [
            10
          ],
          "is_new": false,
          "appearance_count": 1,
          "time_info": "12时58分"
        },
        {
          "title": "电力“隐形心脏”告急！揭秘美国AI热潮最大瓶颈之一：变压器",
          "url": "https://www.cls.cn/detail/2231832",
          "source": "财联社热门",
          "ranks": [
            12
          ],
          "is_new": false,
          "appearance_count": 1,
          "time_info": "12时58分"
        },
        {
          "title": "虞书欣ThaiMu",
          "url": "https://s.weibo.com/weibo?q=%23%E8%99%9E%E4%B9%A6%E6%AC%A3ThaiMu%23&t=31&band_rank=13&Refer=top",
          "source": "微博",
          "ranks": [
            13
          ],
          "is_new": false,
          "appearance_count": 1,
          "time_info": "12时58分"
        },
        {
          "title": "金十数据整理：每日人工智能动态汇总（2025-12-17）",
          "url": "https://flash.jin10.com/detail/20251217115517049800",
          "source": "金十数据",
          "ranks": [
            14
          ],
          "is_new": false,
          "appearance_count": 1,
          "time_info": "12时58分"
        },
        {
          "title": "韩国测试借助人工智能监测冬季危险路况",
          "url": "https://wallstreetcn.com/livenews/3022093",
          "source": "华尔街见闻-快讯",
          "ranks": [
            30
          ],
          "is_new": false,
          "appearance_count": 1,
          "time_info": "12时58分"
        }
      ]
    },
    {
      "keyword_group": "特朗普",
      "match_count": 7,
      "titles": [
        {
          "title": "特朗普政府宣布对40国实施入境限制",
          "url": "https://search.bilibili.com/all?keyword=%E7%89%B9%E6%9C%97%E6%99%AE%E6%94%BF%E5%BA%9C%E5%AE%A3%E5%B8%83%E5%AF%B940%E5%9B%BD%E5%AE%9E%E6%96%BD%E5%85%A5%E5%A2%83%E9%99%90%E5%88%B6",
          "source": "bilibili 热搜",
          "ranks": [
            2
          ],
          "is_new": false,
          "appearance_count": 1,
          "time_info": "12时58分"
        },
        {
          "title": "特朗普：认定委内瑞拉现政府是“外国恐怖组织”",
          "url": "https://news.ifeng.com/c/8p9PufcVOa6",
          "source": "凤凰网",
          "ranks": [
            3
          ],
          "is_new": false,
          "appearance_count": 1,
          "time_info": "12时58分"
        },
        {
          "title": "特朗普签署公告，进一步限制外国公民入境美国",
          "url": "https://news.ifeng.com/c/8p9E57zE6bJ",
          "source": "凤凰网",
          "ranks": [
            5
          ],
          "is_new": false,
          "appearance_count": 1,
          "time_info": "12时58分"
        },
        {
          "title": "特朗普有“酒鬼性格”，万斯“阴谋论者”，马斯克“嗑药的怪人”...“白宫大管家”的炸裂采访爆了",
          "url": "https://wallstreetcn.com/articles/3761525",
          "source": "华尔街见闻",
          "ranks": [
            10
          ],
          "is_new": false,
          "appearance_count": 1,
          "time_info": "12时58分"
        },
        {
          "title": "特朗普称自己执政近一年来在经济方面取得了成功，但赢得中期选举很困难，赢的概率有多大？会有哪些影响？",
          "url": "https://www.zhihu.com/question/1983941746871264912",
          "source": "知乎",
          "ranks": [
            13
          ],
          "is_new": false,
          "appearance_count": 1,
          "time_info": "12时58分"
        },
        {
          "title": "特朗普下令封锁所有受制裁委油轮",
          "url": "https://www.baidu.com/s?wd=%E7%89%B9%E6%9C%97%E6%99%AE%E4%B8%8B%E4%BB%A4%E5%B0%81%E9%94%81%E6%89%80%E6%9C%89%E5%8F%97%E5%88%B6%E8%A3%81%E5%A7%94%E6%B2%B9%E8%BD%AE",
          "source": "百度热搜",
          "ranks": [
            17
          ],
          "is_new": false,
          "appearance_count": 1,
          "time_info": "12时58分"
        },
        {
          "title": "特朗普称已下令封锁进出委受制裁油轮",
          "url": "https://www.toutiao.com/trending/7584624870806277638/",
          "source": "今日头条",
          "ranks": [
            27
          ],
          "is_new": false,
          "appearance_count": 1,
          "time_info": "12时58分"
        }
      ]
    },
    {
      "keyword_group": "中国",
      "match_count": 7,
      "titles": [
        {
          "title": "中国脑机接口实现新突破",
          "url": "https://search.bilibili.com/all?keyword=%E4%B8%AD%E5%9B%BD%E8%84%91%E6%9C%BA%E6%8E%A5%E5%8F%A3%E5%AE%9E%E7%8E%B0%E6%96%B0%E7%AA%81%E7%A0%B4",
          "source": "bilibili 热搜",
          "ranks": [
            1
          ],
          "is_new": false,
          "appearance_count": 1,
          "time_info": "12时58分"
        },
        {
          "title": "2025中国经济印记",
          "url": "https://www.douyin.com/hot/2338915",
          "source": "抖音",
          "ranks": [
            3
          ],
          "is_new": false,
          "appearance_count": 1,
          "time_info": "12时58分"
        },
        {
          "title": "中国国新：要高质量运营中央企业战略性新兴产业发展专项基金、国新创投基金",
          "url": "https://wallstreetcn.com/livenews/3022131",
          "source": "华尔街见闻-快讯",
          "ranks": [
            5
          ],
          "is_new": false,
          "appearance_count": 1,
          "time_info": "12时58分"
        },
        {
          "title": "39岁中国女子伦敦被刺身亡",
          "url": "https://www.baidu.com/s?wd=39%E5%B2%81%E4%B8%AD%E5%9B%BD%E5%A5%B3%E5%AD%90%E4%BC%A6%E6%95%A6%E8%A2%AB%E5%88%BA%E8%BA%AB%E4%BA%A1",
          "source": "百度热搜",
          "ranks": [
            7
          ],
          "is_new": false,
          "appearance_count": 1,
          "time_info": "12时58分"
        },
        {
          "title": "金十图示：2025年12月17日（周三）富时中国A50指数成分股午盘收盘行情一览：通信设备、保险板块领涨，新易盛涨超6%，煤炭板块跌幅居前",
          "url": "https://flash.jin10.com/detail/20251217113649052800",
          "source": "金十数据",
          "ranks": [
            19
          ],
          "is_new": false,
          "appearance_count": 1,
          "time_info": "12时58分"
        },
        {
          "title": "菲方人员持长刀挑衅中国海警",
          "url": "https://www.toutiao.com/trending/7584190038892809764/",
          "source": "今日头条",
          "ranks": [
            23
          ],
          "is_new": false,
          "appearance_count": 1,
          "time_info": "12时58分"
        },
        {
          "title": "中国财政部发行28天期债券，规模400亿元，发行利率1.1220%，边际利率1.3049%，预期1.2500%，投标倍数2.09倍，边际倍数1.24倍； 中国财政部发行91天期债券，规模600亿元，发行利率1.2957%，边际利率1.3442%，预期1.3500%，投标倍数2.69倍，边际倍数2.32倍。",
          "url": "https://wallstreetcn.com/livenews/3022109",
          "source": "华尔街见闻-快讯",
          "ranks": [
            23
          ],
          "is_new": false,
          "appearance_count": 1,
          "time_info": "12时58分"
        }
      ]
    }
  ],
  "report_image_url": "https://joyce677.github.io/TrendRadar/img/news.jpg"
}